LICENSE
MANIFEST.in
README.rst
irc.py
setup.py
botnet/__init__.py
botnet/boss.py
botnet/launcher.py
botnet/worker.py
bots/__init__.py
bots/ascii.py
bots/googlebot.py
bots/lolbot.py
bots/markov.py
bots/quote.py
bots/redisbot.py
bots/yahoo.py
irckit.egg-info/PKG-INFO
irckit.egg-info/SOURCES.txt
irckit.egg-info/dependency_links.txt
irckit.egg-info/top_level.txt