Metadata-Version: 1.1
Name: irckit
Version: 0.1.1
Summary: tinkering with a made-from-scratch irc library in python
Home-page: http://github.com/coleifer/irc/
Author: Charles Leifer
Author-email: coleifer@gmail.com
License: UNKNOWN
Platform: UNKNOWN
Classifier: Development Status :: 4 - Beta
Classifier: Environment :: Web Environment
Classifier: Intended Audience :: Developers
Classifier: License :: OSI Approved :: MIT License
Classifier: Operating System :: OS Independent
Classifier: Programming Language :: Python
